pykauriid/__init__.py
pykauriid/attestations.py
pykauriid/claims.py
pykauriid/config.py
pykauriid/messages.py
pykauriid/utils.py
pykauriid/scripts/__init__.py
pykauriid/scripts/attestations.py
pykauriid/scripts/claims.py
pykauriid/scripts/kauriid.py
pykauriid-0.3.0.dist-info/METADATA
pykauriid-0.3.0.dist-info/RECORD
pykauriid-0.3.0.dist-info/WHEEL
pykauriid-0.3.0.dist-info/dependency_links.txt
pykauriid-0.3.0.dist-info/top_level.txt
